aspera/__init__.py
aspera/lang/__init__.py
aspera/lang/macros.py
aspera/lang/module_loader.py
aspera/lang/parser.py
aspera/lang/type_checker.py
aspera/lang/types.py
aspera/runtime/__init__.py
aspera/runtime/async_engine.py
aspera/runtime/cache.py
aspera/runtime/engine.py
aspera/runtime/error_handler.py
aspera/runtime/memory.py
aspera/runtime/otel.py
aspera/runtime/policy.py
aspera/runtime/resource_limits.py
aspera/runtime/symbolic.py
aspera/runtime/thresholds.py
aspera/runtime/llm_adapters/__init__.py
aspera/runtime/llm_adapters/anthropic_adapter.py
aspera/runtime/llm_adapters/gemini_adapter.py
aspera/runtime/llm_adapters/groq_adapter.py
aspera/runtime/llm_adapters/huggingface_adapter.py
aspera/runtime/llm_adapters/llm_router.py
aspera/runtime/llm_adapters/ollama_adapter.py
aspera/runtime/llm_adapters/openai_adapter.py
aspera/sdk/__init__.py
aspera/sdk/client.py
aspera/sdk/utils.py
aspera/tools/lsp_server.py
aspera/web/__init__.py
aspera/web/api.py
aspera-0.10.5.dist-info/licenses/LICENSE
aspera-0.10.5.dist-info/METADATA
aspera-0.10.5.dist-info/WHEEL
aspera-0.10.5.dist-info/entry_points.txt
aspera-0.10.5.dist-info/top_level.txt
aspera-0.10.5.dist-info/RECORD
