Metadata-Version: 2.4
Name: aspera
Version: 0.10.5
Summary: Linguaggio cognitivo ibrido con runtime Python, integrazione LLM e UI interattiva
Author-email: Christian Quintino De Luca <info@rthitalia.com>
License: BUSL-1.1
Project-URL: Homepage, https://github.com/rthitalia/aspera
Project-URL: Documentation, https://github.com/rthitalia/aspera/docs
Project-URL: Repository, https://github.com/rthitalia/aspera
Classifier: Development Status :: 3 - Alpha
Classifier: Intended Audience :: Developers
Classifier: Intended Audience :: Science/Research
Classifier: Programming Language :: Python :: 3
Classifier: Programming Language :: Python :: 3.10
Classifier: Programming Language :: Python :: 3.11
Classifier: Programming Language :: Python :: 3.12
Classifier: Topic :: Scientific/Engineering :: Artificial Intelligence
Classifier: Topic :: Software Development :: Interpreters
Requires-Python: >=3.10
License-File: LICENSE
Requires-Dist: fastapi>=0.104.0
Requires-Dist: uvicorn[standard]>=0.24.0
Requires-Dist: pydantic>=2.4.0
Requires-Dist: pydantic-settings>=2.0.0
Requires-Dist: python-dotenv>=1.0.0
Requires-Dist: httpx>=0.25.0
Requires-Dist: groq>=0.4.0
Requires-Dist: jsonschema>=4.19.0
Requires-Dist: click>=8.1.0
Requires-Dist: rich>=13.6.0
Requires-Dist: numpy>=1.24.0
Requires-Dist: python-multipart>=0.0.6
Requires-Dist: psutil>=5.9.0
Requires-Dist: pygls>=1.3.1
Requires-Dist: opentelemetry-api>=1.24.0
Requires-Dist: opentelemetry-sdk>=1.24.0
Requires-Dist: opentelemetry-exporter-otlp>=1.24.0
Provides-Extra: dev
Requires-Dist: pytest>=7.4.0; extra == "dev"
Requires-Dist: pytest-cov>=4.1.0; extra == "dev"
Requires-Dist: pytest-asyncio>=0.21.0; extra == "dev"
Requires-Dist: black>=23.10.0; extra == "dev"
Requires-Dist: flake8>=6.1.0; extra == "dev"
Requires-Dist: mypy>=1.6.0; extra == "dev"
Requires-Dist: isort>=5.12.0; extra == "dev"
Dynamic: license-file
